{
    "room_id": "study",
    "room_name": "Study",
    "selected_cards": [],
    "actions": [],
    "action_log": [],
    "players": {
        "c1e412b1-6825-4279-ab1b-c627d61ae64c": {
            "name": "Harvey Dent",
            "admin": true,
            "stage": "Room"
        }
    },
    "turn": 0,
    "closed": false,
    "available_names": [
        "Clark Kent",
        "Bruce Wayne",
        "Diana Prince",
        "Barry Allen",
        "Arthur Curry",
        "Selina Kyle",
        "Edward Nygma",
        "Lex Luthor",
        "Harley Quinn",
        "The Joker",
        "Dick Grayson"
    ]
}